edu_diff_engine/__init__.py
edu_diff_engine/__main__.py
edu_diff_engine/cli.py
edu_diff_engine/engine.py
edu_diff_engine/pdf_processor.py
edu_diff_engine/question_api.py
edu_diff_engine/rubric_extractor.py
edu_diff_engine/skill_vector.py
edu_diff_engine/static_question_rubric.py
edu_diff_engine/static_rubric.py
zetaq_edu_diff_engine-0.1.0.dist-info/METADATA
zetaq_edu_diff_engine-0.1.0.dist-info/WHEEL
zetaq_edu_diff_engine-0.1.0.dist-info/top_level.txt
zetaq_edu_diff_engine-0.1.0.dist-info/RECORD
