Metadata-Version: 2.4
Name: zetaq-edu-diff-engine
Version: 0.1.0
Summary: AI-driven dynamic difficulty question generator with static+dynamic rubrics and 4D skill vectors
Author-email: Nilanjan Panda <nilanjan.phy@gmail.com>
License: MIT
Project-URL: homepage, https://github.com/nilparadox/diff_engine
Project-URL: repository, https://github.com/nilparadox/diff_engine
Requires-Python: >=3.9
Requires-Dist: pdfplumber
Requires-Dist: tqdm
Requires-Dist: pydantic
Requires-Dist: pdfminer.six
Requires-Dist: groq
Requires-Dist: openai
